iceflow/__init__.py
iceflow/_version.py
iceflow/iceflow.py
iceflow-0.0.1a2.dist-info/DESCRIPTION.rst
iceflow-0.0.1a2.dist-info/METADATA
iceflow-0.0.1a2.dist-info/RECORD
iceflow-0.0.1a2.dist-info/WHEEL
iceflow-0.0.1a2.dist-info/entry_points.txt
iceflow-0.0.1a2.dist-info/metadata.json
iceflow-0.0.1a2.dist-info/top_level.txt
