Metadata-Version: 2.0
Name: iceflow
Version: 0.0.1a2
Summary: tensorflow meta-framework
Home-page: https://github.com/sclabs/iceflow
Author: Thomas Gilgenast
Author-email: thomasgilgenast@gmail.com
License: UNKNOWN
Platform: UNKNOWN
Classifier: Development Status :: 3 - Alpha
Classifier: Environment :: Console
Classifier: Intended Audience :: Science/Research
Classifier: Programming Language :: Python :: 3 :: Only
Classifier: Topic :: Scientific/Engineering :: Artificial Intelligence
Requires-Dist: dm-sonnet (>=1.11)
Requires-Dist: tensorflow (>=1.3.0)
